cyberstorm/__init__.py
cyberstorm/attestor/__init__.py
cyberstorm/attestor/v1/__init__.py
cyberstorm/attestor/v1/messages_pb2.py
cyberstorm/attestor/v1/messages_pb2.pyi
cyberstorm/attestor/v1/services_pb2.py
cyberstorm/attestor/v1/services_pb2.pyi
cyberstorm_attestor_schemas-1.0.0.dist-info/METADATA
cyberstorm_attestor_schemas-1.0.0.dist-info/WHEEL
cyberstorm_attestor_schemas-1.0.0.dist-info/top_level.txt
cyberstorm_attestor_schemas-1.0.0.dist-info/RECORD
