Metadata-Version: 2.4
Name: cyberstorm-attestor-schemas
Version: 1.0.0
Summary: Protocol Buffer schemas and generated clients for Cyberstorm Attestor service
Author-email: Allen Day <allenday@users.github.com>
License-Expression: MIT
Project-URL: Homepage, https://github.com/cyberstorm-dev/attestor-schemas
Project-URL: Repository, https://github.com/cyberstorm-dev/attestor-schemas.git
Project-URL: Issues, https://github.com/cyberstorm-dev/attestor-schemas/issues
Classifier: Development Status :: 4 - Beta
Classifier: Intended Audience :: Developers
Classifier: Programming Language :: Python :: 3
Classifier: Programming Language :: Python :: 3.8
Classifier: Programming Language :: Python :: 3.9
Classifier: Programming Language :: Python :: 3.10
Classifier: Programming Language :: Python :: 3.11
Classifier: Topic :: Software Development :: Libraries :: Python Modules
Requires-Python: >=3.8
Requires-Dist: protobuf>=4.0.0
Requires-Dist: grpcio>=1.50.0
Requires-Dist: grpcio-tools>=1.50.0
Requires-Dist: googleapis-common-protos>=1.60.0
Provides-Extra: dev
Requires-Dist: pytest>=7.0; extra == "dev"
Requires-Dist: black; extra == "dev"
Requires-Dist: isort; extra == "dev"
Requires-Dist: mypy; extra == "dev"
Requires-Dist: grpcio-status; extra == "dev"
Provides-Extra: build
Requires-Dist: build>=0.10.0; extra == "build"
Requires-Dist: twine>=4.0.0; extra == "build"
